{"cnt":20,"list":[{"coord":{"lon":37.6156,"lat":55.7522},"sys":{"country":"RU","timezone":10800,"sunrise":1739767791,"sunset":1739803052},"weather":[{"id":803,"main":"Clouds","description":"broken clouds","icon":"04d"}],"main":{"temp":-9.77,"feels_like":-16.6,"temp_min":-11.76,"temp_max":-9.07,"pressure":1019,"sea_level":1019,"grnd_level":998,"humidity":58},"visibility":10000,"wind":{"speed":4.35,"deg":275},"clouds":{"all":74},"dt":1739779680,"id":524901,"name":"Moscow"},{"coord":{"lon":139.6917,"lat":35.6895},"sys":{"country":"JP","timezone":32400,"sunrise":1739741188,"sunset":1739780660},"weather":[{"id":802,"main":"Clouds","description":"scattered clouds","icon":"03d"}],"main":{"temp":9.8,"feels_like":5.49,"temp_min":8.7,"temp_max":10.79,"pressure":1003,"sea_level":1003,"grnd_level":1001,"humidity":34},"visibility":10000,"wind":{"speed":12.35,"deg":340},"clouds":{"all":40},"dt":1739779754,"id":1850147,"name":"Tokyo"},{"coord":{"lon":151.2073,"lat":-33.8679},"sys":{"country":"AU","timezone":39600,"sunrise":1739734333,"sunset":1739781988},"weather":[{"id":801,"main":"Clouds","description":"few clouds","icon":"02d"}],"main":{"temp":20.41,"feels_like":19.97,"temp_min":19.84,"temp_max":20.94,"pressure":1017,"sea_level":1017,"grnd_level":1012,"humidity":56},"visibility":10000,"wind":{"speed":8.23,"deg":160},"clouds":{"all":20},"dt":1739779744,"id":2147714,"name":"Sydney"},{"coord":{"lon":174.7756,"lat":-41.2866},"sys":{"country":"NZ","timezone":46800,"sunrise":1739728026,"sunset":1739776983},"weather":[{"id":804,"main":"Clouds","description":"overcast clouds","icon":"04n"}],"main":{"temp":21.81,"feels_like":21.82,"temp_min":21.81,"temp_max":21.81,"pressure":1007,"sea_level":1007,"grnd_level":995,"humidity":68},"visibility":10000,"wind":{"speed":5.66,"deg":40},"clouds":{"all":100},"dt":1739779755,"id":2179537,"name":"Wellington"},{"coord":{"lon":77.2167,"lat":28.6667},"sys":{"country":"IN","timezone":19800,"sunrise":1739755685,"sunset":1739796150},"weather":[{"id":721,"main":"Haze","description":"haze","icon":"50d"}],"main":{"temp":26.05,"feels_like":26.05,"temp_min":26.05,"temp_max":26.05,"pressure":1014,"sea_level":1014,"grnd_level":989,"humidity":27},"visibility":4000,"wind":{"speed":1.54,"deg":260},"clouds":{"all":63},"dt":1739779751,"id":1273294,"name":"Delhi"},{"coord":{"lon":116.3972,"lat":39.9075},"sys":{"country":"CN","timezone":28800,"sunrise":1739747110,"sunset":1739785920},"weather":[{"id":800,"main":"Clear","description":"clear sky","icon":"01d"}],"main":{"temp":4.94,"feels_like":3.67,"temp_min":4.94,"temp_max":4.94,"pressure":1030,"sea_level":1030,"grnd_level":1025,"humidity":12},"visibility":10000,"wind":{"speed":1.67,"deg":177},"clouds":{"all":0},"dt":1739779749,"id":1816670,"name":"Beijing"},{"coord":{"lon":48.6693,"lat":31.3203},"sys":{"country":"IR","timezone":12600,"sunrise":1739762707,"sunset":1739802830},"weather":[{"id":801,"main":"Clouds","description":"few clouds","icon":"02d"}],"main":{"temp":17.97,"feels_like":17.26,"temp_min":17.97,"temp_max":17.97,"pressure":1020,"sea_level":1020,"grnd_level":1018,"humidity":55},"visibility":7000,"wind":{"speed":1.03,"deg":290},"clouds":{"all":20},"dt":1739779743,"id":144448,"name":"Ahvaz"},{"coord":{"lon":18.4232,"lat":-33.9258},"sys":{"country":"ZA","timezone":7200,"sunrise":1739766217,"sunset":1739813838},"weather":[{"id":800,"main":"Clear","description":"clear sky","icon":"01d"}],"main":{"temp":23.49,"feels_like":23.62,"temp_min":23.28,"temp_max":23.95,"pressure":1011,"sea_level":1011,"grnd_level":1010,"humidity":66},"visibility":10000,"wind":{"speed":4.47,"deg":164},"clouds":{"all":0},"dt":1739779760,"id":3369157,"name":"Cape Town"},{"coord":{"lon":2.3486,"lat":48.8534},"sys":{"country":"FR","timezone":3600,"sunrise":1739775323,"sunset":1739812448},"weather":[{"id":800,"main":"Clear","description":"clear sky","icon":"01d"}],"main":{"temp":-0.61,"feels_like":-4.74,"temp_min":-1.55,"temp_max":-0.12,"pressure":1021,"sea_level":1021,"grnd_level":1011,"humidity":89},"visibility":10000,"wind":{"speed":3.6,"deg":70},"clouds":{"all":0},"dt":1739779925,"id":2988506,"name":"Paris"},{"coord":{"lon":10.45,"lat":54.0333},"sys":{"country":"DE","timezone":3600,"sunrise":1739774042,"sunset":1739809840},"weather":[{"id":801,"main":"Clouds","description":"few clouds","icon":"02d"}],"main":{"temp":-3.35,"feels_like":-3.35,"temp_min":-3.35,"temp_max":-3.35,"pressure":1028,"sea_level":1028,"grnd_level":1023,"humidity":99},"visibility":10000,"wind":{"speed":0.67,"deg":174},"clouds":{"all":11},"dt":1739779919,"id":2950158,"name":"Berlin"},{"coord":{"lon":10.7461,"lat":59.9127},"sys":{"country":"NO","timezone":3600,"sunrise":1739774969,"sunset":1739808771},"weather":[{"id":804,"main":"Clouds","description":"overcast clouds","icon":"04d"}],"main":{"temp":-8.41,"feels_like":-11.79,"temp_min":-8.41,"temp_max":-8.41,"pressure":1024,"sea_level":1024,"grnd_level":998,"humidity":79},"visibility":10000,"wind":{"speed":1.73,"deg":317},"clouds":{"all":100},"dt":1739779759,"id":3143244,"name":"Oslo"},{"coord":{"lon":-0.1257,"lat":51.5085},"sys":{"country":"GB","timezone":0,"sunrise":1739776235,"sunset":1739812723},"weather":[{"id":801,"main":"Clouds","description":"few clouds","icon":"02d"}],"main":{"temp":-0.51,"feels_like":-3.54,"temp_min":-1.95,"temp_max":0.1,"pressure":1023,"sea_level":1023,"grnd_level":1018,"humidity":92},"visibility":10000,"wind":{"speed":2.42,"deg":107},"clouds":{"all":11},"dt":1739779757,"id":2643743,"name":"London"},{"coord":{"lon":-74.006,"lat":40.7143},"sys":{"country":"US","timezone":-18000,"sunrise":1739792833,"sunset":1739831586},"weather":[{"id":803,"main":"Clouds","description":"broken clouds","icon":"04n"}],"main":{"temp":0.49,"feels_like":-6.51,"temp_min":-0.58,"temp_max":1.19,"pressure":1002,"sea_level":1002,"grnd_level":1001,"humidity":50},"visibility":10000,"wind":{"speed":13.38,"deg":270},"clouds":{"all":75},"dt":1739780041,"id":5128581,"name":"New York"},{"coord":{"lon":-118.2437,"lat":34.0522},"sys":{"country":"US","timezone":-28800,"sunrise":1739802927,"sunset":1739842725},"weather":[{"id":800,"main":"Clear","description":"clear sky","icon":"01n"}],"main":{"temp":12.96,"feels_like":12.17,"temp_min":11.49,"temp_max":14.89,"pressure":1014,"sea_level":1014,"grnd_level":995,"humidity":71},"visibility":10000,"wind":{"speed":0,"deg":0},"clouds":{"all":0},"dt":1739780048,"id":5368361,"name":"Los Angeles"},{"coord":{"lon":-123.1193,"lat":49.2497},"sys":{"country":"CA","timezone":-28800,"sunrise":1739805442,"sunset":1739842549},"weather":[{"id":500,"main":"Rain","description":"light rain","icon":"10n"}],"main":{"temp":4.73,"feels_like":4.73,"temp_min":3.47,"temp_max":5.57,"pressure":1009,"sea_level":1009,"grnd_level":1001,"humidity":91},"visibility":10000,"wind":{"speed":0.89,"deg":55},"clouds":{"all":100},"dt":1739780061,"id":6173331,"name":"Vancouver"},{"coord":{"lon":-76.6389,"lat":-12.0039},"sys":{"country":"PE","timezone":-18000,"sunrise":1739790419,"sunset":1739835263},"weather":[{"id":804,"main":"Clouds","description":"overcast clouds","icon":"04n"}],"main":{"temp":14.74,"feels_like":14.67,"temp_min":14.74,"temp_max":14.74,"pressure":1014,"sea_level":1014,"grnd_level":819,"humidity":92},"visibility":10000,"wind":{"speed":1.56,"deg":271},"clouds":{"all":100},"dt":1739779812,"id":3936452,"name":"Lima region"},{"coord":{"lon":-42.5,"lat":-22},"sys":{"country":"BR","timezone":-10800,"sunrise":1739781658,"sunset":1739827639},"weather":[{"id":800,"main":"Clear","description":"clear sky","icon":"01n"}],"main":{"temp":18.46,"feels_like":18.48,"temp_min":18.46,"temp_max":18.46,"pressure":1015,"sea_level":1015,"grnd_level":946,"humidity":81},"visibility":10000,"wind":{"speed":1.77,"deg":201},"clouds":{"all":0},"dt":1739780001,"id":3451189,"name":"State of Rio de Janeiro"},{"coord":{"lon":-68.3,"lat":-54.8},"sys":{"country":"AR","timezone":-10800,"sunrise":1739784715,"sunset":1739836965},"weather":[{"id":804,"main":"Clouds","description":"overcast clouds","icon":"04n"}],"main":{"temp":-1.05,"feels_like":-3.94,"temp_min":-1.05,"temp_max":-1.05,"pressure":1013,"sea_level":1013,"grnd_level":1007,"humidity":95},"visibility":10000,"wind":{"speed":2.21,"deg":339},"clouds":{"all":100},"dt":1739779743,"id":3833367,"name":"Ushuaia"},{"coord":{"lon":129.7331,"lat":62.0339},"sys":{"country":"RU","timezone":32400,"sunrise":1739746930,"sunset":1739779698},"weather":[{"id":800,"main":"Clear","description":"clear sky","icon":"01n"}],"main":{"temp":-18.02,"feels_like":-25.02,"temp_min":-18.02,"temp_max":-18.02,"pressure":1032,"sea_level":1032,"grnd_level":1019,"humidity":60},"visibility":10000,"wind":{"speed":5,"deg":290},"clouds":{"all":0},"dt":1739779755,"id":2013159,"name":"Yakutsk"},{"coord":{"lon":88.2027,"lat":69.3535},"sys":{"country":"RU","timezone":25200,"sunrise":1739759238,"sunset":1739787324},"weather":[{"id":803,"main":"Clouds","description":"broken clouds","icon":"04d"}],"main":{"temp":-24.85,"feels_like":-31.85,"temp_min":-24.85,"temp_max":-24.85,"pressure":1037,"sea_level":1037,"grnd_level":1030,"humidity":90},"visibility":10000,"wind":{"speed":4.01,"deg":123},"clouds":{"all":59},"dt":1739779752,"id":1497337,"name":"Noril'sk"}]}