{"cnt":20,"list":[{"coord":{"lon":37.6156,"lat":55.7522},"sys":{"country":"RU","timezone":10800,"sunrise":1698899793,"sunset":1698932973},"weather":[{"id":500,"main":"Rain","description":"light rain","icon":"10n"}],"main":{"temp":9.94,"feels_like":7.74,"temp_min":8.94,"temp_max":11.1,"pressure":1001,"sea_level":1001,"grnd_level":984,"humidity":94},"visibility":10000,"wind":{"speed":4.43,"deg":350},"clouds":{"all":100},"dt":1698897908,"id":524901,"name":"Moscow"},{"coord":{"lon":139.6917,"lat":35.6895},"sys":{"country":"JP","timezone":32400,"sunrise":1698872601,"sunset":1698911169},"weather":[{"id":800,"main":"Clear","description":"clear sky","icon":"01d"}],"main":{"temp":25.79,"feels_like":25.47,"temp_min":23.69,"temp_max":26.99,"pressure":1015,"humidity":40},"visibility":10000,"wind":{"speed":0.89,"deg":157},"clouds":{"all":0},"dt":1698898155,"id":1850147,"name":"Tokyo"},{"coord":{"lon":151.2073,"lat":-33.8679},"sys":{"country":"AU","timezone":39600,"sunrise":1698864868,"sunset":1698913374},"weather":[{"id":802,"main":"Clouds","description":"scattered clouds","icon":"03d"}],"main":{"temp":21.58,"feels_like":21.23,"temp_min":19.28,"temp_max":25.5,"pressure":1019,"humidity":55},"visibility":10000,"wind":{"speed":7.2,"deg":120},"clouds":{"all":40},"dt":1698898143,"id":2147714,"name":"Sydney"},{"coord":{"lon":174.7756,"lat":-41.2866},"sys":{"country":"NZ","timezone":46800,"sunrise":1698858435,"sunset":1698908495},"weather":[{"id":804,"main":"Clouds","description":"overcast clouds","icon":"04d"}],"main":{"temp":15.21,"feels_like":15.11,"temp_min":14.92,"temp_max":17.81,"pressure":1015,"humidity":89},"visibility":10000,"wind":{"speed":6.69,"deg":350},"clouds":{"all":100},"dt":1698898157,"id":2179537,"name":"Wellington"},{"coord":{"lon":77.2167,"lat":28.6667},"sys":{"country":"IN","timezone":19800,"sunrise":1698887004,"sunset":1698926754},"weather":[{"id":711,"main":"Smoke","description":"smoke","icon":"50d"}],"main":{"temp":22.05,"feels_like":22.09,"temp_min":22.05,"temp_max":22.05,"pressure":1018,"humidity":68},"visibility":1200,"wind":{"speed":0,"deg":0},"clouds":{"all":1},"dt":1698898151,"id":1273294,"name":"Delhi"},{"coord":{"lon":116.3972,"lat":39.9075},"sys":{"country":"CN","timezone":28800,"sunrise":1698878609,"sunset":1698916342},"weather":[{"id":800,"main":"Clear","description":"clear sky","icon":"01d"}],"main":{"temp":18.94,"feels_like":18.12,"temp_min":18.94,"temp_max":18.94,"pressure":1008,"sea_level":1008,"grnd_level":1002,"humidity":47},"visibility":10000,"wind":{"speed":1.42,"deg":197},"clouds":{"all":5},"dt":1698898147,"id":1816670,"name":"Beijing"},{"coord":{"lon":48.6693,"lat":31.3203},"sys":{"country":"IR","timezone":12600,"sunrise":1698894076,"sunset":1698933385},"weather":[{"id":741,"main":"Fog","description":"fog","icon":"50d"},{"id":721,"main":"Haze","description":"haze","icon":"50d"}],"main":{"temp":20.97,"feels_like":20.9,"temp_min":20.97,"temp_max":20.97,"pressure":1014,"humidity":68},"visibility":1800,"wind":{"speed":0,"deg":0},"clouds":{"all":67},"dt":1698898142,"id":144448,"name":"Ahvaz"},{"coord":{"lon":18.4232,"lat":-33.9258},"sys":{"country":"ZA","timezone":7200,"sunrise":1698896710,"sunset":1698945269},"weather":[{"id":800,"main":"Clear","description":"clear sky","icon":"01n"}],"main":{"temp":18,"feels_like":17.53,"temp_min":16.86,"temp_max":19.21,"pressure":1011,"humidity":64},"visibility":10000,"wind":{"speed":6.17,"deg":170},"clouds":{"all":0},"dt":1698894940,"id":3369157,"name":"Cape Town"},{"coord":{"lon":2.3486,"lat":48.8534},"sys":{"country":"FR","timezone":3600,"sunrise":1698907096,"sunset":1698942598},"weather":[{"id":803,"main":"Clouds","description":"broken clouds","icon":"04n"}],"main":{"temp":12.17,"feels_like":11.71,"temp_min":11.32,"temp_max":12.88,"pressure":978,"humidity":87},"visibility":10000,"wind":{"speed":10.8,"deg":190},"clouds":{"all":75},"dt":1698894784,"id":2988506,"name":"Paris"},{"coord":{"lon":10.45,"lat":54.0333},"sys":{"country":"DE","timezone":3600,"sunrise":1698905991,"sunset":1698939814},"weather":[{"id":802,"main":"Clouds","description":"scattered clouds","icon":"03n"}],"main":{"temp":9.3,"feels_like":9.3,"temp_min":8.22,"temp_max":9.95,"pressure":994,"sea_level":994,"grnd_level":990,"humidity":95},"visibility":10000,"wind":{"speed":0.45,"deg":169},"clouds":{"all":45},"dt":1698894775,"id":2950158,"name":"Berlin"},{"coord":{"lon":10.7461,"lat":59.9127},"sys":{"country":"NO","timezone":3600,"sunrise":1698907205,"sunset":1698938458},"weather":[{"id":600,"main":"Snow","description":"light snow","icon":"13n"}],"main":{"temp":-1.55,"feels_like":-5.86,"temp_min":-2.34,"temp_max":-0.73,"pressure":1001,"sea_level":1001,"grnd_level":997,"humidity":96},"visibility":138,"wind":{"speed":3.58,"deg":39},"clouds":{"all":100},"dt":1698894891,"id":3143244,"name":"Oslo"},{"coord":{"lon":-0.1257,"lat":51.5085},"sys":{"country":"GB","timezone":0,"sunrise":1698908097,"sunset":1698942785},"weather":[{"id":500,"main":"Rain","description":"light rain","icon":"10n"}],"main":{"temp":9.58,"feels_like":7.68,"temp_min":8.05,"temp_max":11.12,"pressure":962,"humidity":92},"visibility":6000,"wind":{"speed":3.6,"deg":130},"clouds":{"all":20},"dt":1698898157,"id":2643743,"name":"London"},{"coord":{"lon":-74.006,"lat":40.7143},"sys":{"country":"US","timezone":-14400,"sunrise":1698924428,"sunset":1698961916},"weather":[{"id":800,"main":"Clear","description":"clear sky","icon":"01n"}],"main":{"temp":4,"feels_like":0.13,"temp_min":1.31,"temp_max":5.55,"pressure":1026,"humidity":61},"visibility":10000,"wind":{"speed":4.92,"deg":311},"clouds":{"all":0},"dt":1698895093,"id":5128581,"name":"New York"},{"coord":{"lon":-118.2437,"lat":34.0522},"sys":{"country":"US","timezone":-25200,"sunrise":1698847942,"sunset":1698886838},"weather":[{"id":800,"main":"Clear","description":"clear sky","icon":"01n"}],"main":{"temp":20.94,"feels_like":19.77,"temp_min":18.23,"temp_max":24,"pressure":1019,"humidity":26},"visibility":10000,"wind":{"speed":5.14,"deg":250},"clouds":{"all":0},"dt":1698895131,"id":5368361,"name":"Los Angeles"},{"coord":{"lon":-123.1193,"lat":49.2497},"sys":{"country":"CA","timezone":-25200,"sunrise":1698850803,"sunset":1698886317},"weather":[{"id":804,"main":"Clouds","description":"overcast clouds","icon":"04n"}],"main":{"temp":9.96,"feels_like":8.14,"temp_min":8,"temp_max":11.08,"pressure":1013,"humidity":84},"visibility":10000,"wind":{"speed":3.6,"deg":110},"clouds":{"all":100},"dt":1698895159,"id":6173331,"name":"Vancouver"},{"coord":{"lon":-76.6389,"lat":-12.0039},"sys":{"country":"PE","timezone":-18000,"sunrise":1698834843,"sunset":1698879966},"weather":[{"id":804,"main":"Clouds","description":"overcast clouds","icon":"04n"}],"main":{"temp":9.66,"feels_like":9.66,"temp_min":9.66,"temp_max":9.66,"pressure":1017,"sea_level":1017,"grnd_level":857,"humidity":61},"visibility":10000,"wind":{"speed":0.68,"deg":252},"clouds":{"all":100},"dt":1698895021,"id":3936452,"name":"Lima region"},{"coord":{"lon":-42.5,"lat":-22},"sys":{"country":"BR","timezone":-10800,"sunrise":1698912329,"sunset":1698958893},"weather":[{"id":802,"main":"Clouds","description":"scattered clouds","icon":"03n"}],"main":{"temp":18.76,"feels_like":19.12,"temp_min":18.76,"temp_max":18.76,"pressure":1013,"sea_level":1013,"grnd_level":944,"humidity":93},"visibility":10000,"wind":{"speed":1.34,"deg":202},"clouds":{"all":49},"dt":1698894956,"id":3451189,"name":"State of Rio de Janeiro"},{"coord":{"lon":-68.3,"lat":-54.8},"sys":{"country":"AR","timezone":-10800,"sunrise":1698914573,"sunset":1698969032},"weather":[{"id":800,"main":"Clear","description":"clear sky","icon":"01n"}],"main":{"temp":5.81,"feels_like":2.79,"temp_min":5.81,"temp_max":5.81,"pressure":1003,"humidity":52},"visibility":10000,"wind":{"speed":4.12,"deg":250},"clouds":{"all":0},"dt":1698895013,"id":3833367,"name":"Ushuaia"},{"coord":{"lon":129.7331,"lat":62.0339},"sys":{"country":"RU","timezone":32400,"sunrise":1698879190,"sunset":1698909360},"weather":[{"id":800,"main":"Clear","description":"clear sky","icon":"01d"}],"main":{"temp":-18.02,"feels_like":-25.02,"temp_min":-18.02,"temp_max":-18.02,"pressure":1016,"humidity":65},"visibility":10000,"wind":{"speed":4,"deg":250},"clouds":{"all":0},"dt":1698898156,"id":2013159,"name":"Yakutsk"},{"coord":{"lon":88.2027,"lat":69.3535},"sys":{"country":"RU","timezone":25200,"sunrise":1698892322,"sunset":1698916162},"weather":[{"id":804,"main":"Clouds","description":"overcast clouds","icon":"04d"}],"main":{"temp":-16.43,"feels_like":-22.48,"temp_min":-16.43,"temp_max":-16.43,"pressure":1026,"sea_level":1026,"grnd_level":1020,"humidity":90},"visibility":10000,"wind":{"speed":2.5,"deg":124},"clouds":{"all":100},"dt":1698898152,"id":1497337,"name":"Noril'sk"}]}