{"cnt":20,"list":[{"coord":{"lon":37.6156,"lat":55.7522},"sys":{"country":"RU","timezone":10800,"sunrise":1742182786,"sunset":1742225766},"weather":[{"id":600,"main":"Snow","description":"light snow","icon":"13n"}],"main":{"temp":0.37,"feels_like":-2.42,"temp_min":-0.71,"temp_max":0.37,"pressure":1004,"sea_level":1004,"grnd_level":985,"humidity":54},"wind":{"speed":2.34,"deg":295},"clouds":{"all":100},"dt":1742173446,"id":524901,"name":"Moscow"},{"coord":{"lon":139.6917,"lat":35.6895},"sys":{"country":"JP","timezone":32400,"sunrise":1742158183,"sunset":1742201382},"weather":[{"id":801,"main":"Clouds","description":"few clouds","icon":"02d"}],"main":{"temp":12.79,"feels_like":11.53,"temp_min":11.48,"temp_max":13.66,"pressure":997,"sea_level":997,"grnd_level":995,"humidity":54},"visibility":10000,"wind":{"speed":4.12,"deg":350},"clouds":{"all":20},"dt":1742173756,"id":1850147,"name":"Tokyo"},{"coord":{"lon":151.2073,"lat":-33.8679},"sys":{"country":"AU","timezone":39600,"sunrise":1742154947,"sunset":1742199092},"weather":[{"id":800,"main":"Clear","description":"clear sky","icon":"01d"}],"main":{"temp":20.09,"feels_like":19.38,"temp_min":18.72,"temp_max":21.86,"pressure":1020,"sea_level":1020,"grnd_level":1015,"humidity":47},"visibility":10000,"wind":{"speed":3.58,"deg":168},"clouds":{"all":1},"dt":1742173744,"id":2147714,"name":"Sydney"},{"coord":{"lon":174.7756,"lat":-41.2866},"sys":{"country":"NZ","timezone":46800,"sunrise":1742149189,"sunset":1742193539},"weather":[{"id":803,"main":"Clouds","description":"broken clouds","icon":"04d"}],"main":{"temp":21.81,"feels_like":21.82,"temp_min":21.81,"temp_max":21.81,"pressure":1009,"sea_level":1009,"grnd_level":998,"humidity":68},"visibility":10000,"wind":{"speed":10.8,"deg":350},"clouds":{"all":75},"dt":1742173757,"id":2179537,"name":"Wellington"},{"coord":{"lon":77.2167,"lat":28.6667},"sys":{"country":"IN","timezone":19800,"sunrise":1742173125,"sunset":1742216422},"weather":[{"id":701,"main":"Mist","description":"mist","icon":"50d"}],"main":{"temp":17.05,"feels_like":17.11,"temp_min":17.05,"temp_max":17.05,"pressure":1012,"sea_level":1012,"grnd_level":987,"humidity":88},"visibility":2500,"wind":{"speed":1.03,"deg":230},"clouds":{"all":40},"dt":1742173752,"id":1273294,"name":"Delhi"},{"coord":{"lon":116.3972,"lat":39.9075},"sys":{"country":"CN","timezone":28800,"sunrise":1742163794,"sunset":1742206950},"weather":[{"id":800,"main":"Clear","description":"clear sky","icon":"01d"}],"main":{"temp":6.94,"feels_like":3.37,"temp_min":6.94,"temp_max":6.94,"pressure":1021,"sea_level":1021,"grnd_level":1016,"humidity":26},"visibility":10000,"wind":{"speed":5.98,"deg":340},"clouds":{"all":0},"dt":1742173749,"id":1816670,"name":"Beijing"},{"coord":{"lon":48.6693,"lat":31.3203},"sys":{"country":"IR","timezone":12600,"sunrise":1742179984,"sunset":1742223263},"weather":[{"id":803,"main":"Clouds","description":"broken clouds","icon":"04n"}],"main":{"temp":21.88,"feels_like":20.8,"temp_min":21.88,"temp_max":21.88,"pressure":1014,"sea_level":1014,"grnd_level":1012,"humidity":26},"visibility":10000,"wind":{"speed":2.63,"deg":281},"clouds":{"all":78},"dt":1742173742,"id":144448,"name":"Ahvaz"},{"coord":{"lon":18.4232,"lat":-33.9258},"sys":{"country":"ZA","timezone":7200,"sunrise":1742186831,"sunset":1742230930},"weather":[{"id":803,"main":"Clouds","description":"broken clouds","icon":"04n"}],"main":{"temp":17.23,"feels_like":17.25,"temp_min":16.86,"temp_max":17.93,"pressure":1019,"sea_level":1019,"grnd_level":1018,"humidity":86},"visibility":10000,"wind":{"speed":5.81,"deg":191},"clouds":{"all":69},"dt":1742173762,"id":3369157,"name":"Cape Town"},{"coord":{"lon":2.3486,"lat":48.8534},"sys":{"country":"FR","timezone":3600,"sunrise":1742191186,"sunset":1742234290},"weather":[{"id":800,"main":"Clear","description":"clear sky","icon":"01n"}],"main":{"temp":4.72,"feels_like":0.92,"temp_min":3.1,"temp_max":5.76,"pressure":1023,"sea_level":1023,"grnd_level":1013,"humidity":68},"visibility":10000,"wind":{"speed":5.14,"deg":40},"clouds":{"all":0},"dt":1742173926,"id":2988506,"name":"Paris"},{"coord":{"lon":10.45,"lat":54.0333},"sys":{"country":"DE","timezone":3600,"sunrise":1742189280,"sunset":1742232308},"weather":[{"id":800,"main":"Clear","description":"clear sky","icon":"01n"}],"main":{"temp":0.54,"feels_like":-4.48,"temp_min":0.54,"temp_max":1.61,"pressure":1027,"sea_level":1027,"grnd_level":1021,"humidity":72},"visibility":10000,"wind":{"speed":5.44,"deg":56},"clouds":{"all":3},"dt":1742173920,"id":2950158,"name":"Berlin"},{"coord":{"lon":10.7461,"lat":59.9127},"sys":{"country":"NO","timezone":3600,"sunrise":1742189259,"sunset":1742232187},"weather":[{"id":800,"main":"Clear","description":"clear sky","icon":"01n"}],"main":{"temp":-4.4,"feels_like":-6.62,"temp_min":-4.4,"temp_max":-4.4,"pressure":1030,"sea_level":1030,"grnd_level":1004,"humidity":82},"visibility":10000,"wind":{"speed":1.42,"deg":318},"clouds":{"all":10},"dt":1742173761,"id":3143244,"name":"Oslo"},{"coord":{"lon":-0.1257,"lat":51.5085},"sys":{"country":"GB","timezone":0,"sunrise":1742191796,"sunset":1742234867},"weather":[{"id":803,"main":"Clouds","description":"broken clouds","icon":"04n"}],"main":{"temp":6.02,"feels_like":3.67,"temp_min":5.01,"temp_max":6.77,"pressure":1027,"sea_level":1027,"grnd_level":1023,"humidity":84},"visibility":10000,"wind":{"speed":3.09,"deg":30},"clouds":{"all":75},"dt":1742173759,"id":2643743,"name":"London"},{"coord":{"lon":-74.006,"lat":40.7143},"sys":{"country":"US","timezone":-14400,"sunrise":1742123143,"sunset":1742166212},"weather":[{"id":721,"main":"Haze","description":"haze","icon":"50n"}],"main":{"temp":13.96,"feels_like":13.74,"temp_min":12.19,"temp_max":15.97,"pressure":1012,"sea_level":1012,"grnd_level":1010,"humidity":89},"visibility":10000,"wind":{"speed":8.23,"deg":180},"clouds":{"all":100},"dt":1742174046,"id":5128581,"name":"New York"},{"coord":{"lon":-118.2437,"lat":34.0522},"sys":{"country":"US","timezone":-25200,"sunrise":1742133701,"sunset":1742176883},"weather":[{"id":800,"main":"Clear","description":"clear sky","icon":"01d"}],"main":{"temp":16.81,"feels_like":16.06,"temp_min":13.7,"temp_max":19.4,"pressure":1019,"sea_level":1019,"grnd_level":1000,"humidity":58},"visibility":10000,"wind":{"speed":3.6,"deg":290},"clouds":{"all":0},"dt":1742173767,"id":5368361,"name":"Los Angeles"},{"coord":{"lon":-123.1193,"lat":49.2497},"sys":{"country":"CA","timezone":-25200,"sunrise":1742134984,"sunset":1742177940},"weather":[{"id":804,"main":"Clouds","description":"overcast clouds","icon":"04d"}],"main":{"temp":7.93,"feels_like":4.1,"temp_min":7.35,"temp_max":8.47,"pressure":1004,"sea_level":1004,"grnd_level":996,"humidity":75},"visibility":10000,"wind":{"speed":7.6,"deg":180},"clouds":{"all":100},"dt":1742174065,"id":6173331,"name":"Vancouver"},{"coord":{"lon":-76.6389,"lat":-12.0039},"sys":{"country":"PE","timezone":-18000,"sunrise":1742123424,"sunset":1742167194},"weather":[{"id":804,"main":"Clouds","description":"overcast clouds","icon":"04n"}],"main":{"temp":15.84,"feels_like":15.65,"temp_min":15.84,"temp_max":15.84,"pressure":1018,"sea_level":1018,"grnd_level":822,"humidity":83},"visibility":10000,"wind":{"speed":0.57,"deg":327},"clouds":{"all":100},"dt":1742173821,"id":3936452,"name":"Lima region"},{"coord":{"lon":-42.5,"lat":-22},"sys":{"country":"BR","timezone":-10800,"sunrise":1742115145,"sunset":1742159090},"weather":[{"id":804,"main":"Clouds","description":"overcast clouds","icon":"04n"}],"main":{"temp":19.9,"feels_like":20.48,"temp_min":19.9,"temp_max":19.9,"pressure":1019,"sea_level":1019,"grnd_level":949,"humidity":97},"visibility":10000,"wind":{"speed":1.31,"deg":139},"clouds":{"all":100},"dt":1742173995,"id":3451189,"name":"State of Rio de Janeiro"},{"coord":{"lon":-68.3,"lat":-54.8},"sys":{"country":"AR","timezone":-10800,"sunrise":1742120819,"sunset":1742165797},"weather":[{"id":803,"main":"Clouds","description":"broken clouds","icon":"04n"}],"main":{"temp":7.3,"feels_like":4.68,"temp_min":7.3,"temp_max":7.3,"pressure":998,"sea_level":998,"grnd_level":992,"humidity":91},"visibility":10000,"wind":{"speed":4,"deg":357},"clouds":{"all":82},"dt":1742173742,"id":3833367,"name":"Ushuaia"},{"coord":{"lon":129.7331,"lat":62.0339},"sys":{"country":"RU","timezone":32400,"sunrise":1742160788,"sunset":1742203556},"weather":[{"id":600,"main":"Snow","description":"light snow","icon":"13d"}],"main":{"temp":-26.02,"feels_like":-26.02,"temp_min":-26.02,"temp_max":-26.02,"pressure":1021,"sea_level":1021,"grnd_level":1008,"humidity":70},"visibility":10000,"wind":{"speed":1,"deg":20},"clouds":{"all":100},"dt":1742173756,"id":2013159,"name":"Yakutsk"},{"coord":{"lon":88.2027,"lat":69.3535},"sys":{"country":"RU","timezone":25200,"sunrise":1742170846,"sunset":1742213429},"weather":[{"id":803,"main":"Clouds","description":"broken clouds","icon":"04d"}],"main":{"temp":-15.28,"feels_like":-22.28,"temp_min":-15.28,"temp_max":-15.28,"pressure":1010,"sea_level":1010,"grnd_level":1003,"humidity":90},"visibility":10000,"wind":{"speed":4.28,"deg":147},"clouds":{"all":56},"dt":1742173753,"id":1497337,"name":"Noril'sk"}]}